{
    "asset": {
        "version": "1.1"
    },
    "root": {
        "children": [
            {
                "children": [
                    {
                        "children": [
                            {
                                "boundingVolume": {
                                    "sphere": [
                                        -3130.757957048342,
                                        -1490.5980222362198,
                                        36.54719439730136,
                                        514.1903144513892
                                    ]
                                },
                                "geometricError": 82270.45421847233,
                                "refine": "REPLACE",
                                "content": {
                                    "url": "Tile_-4735_15833_0000_0000_0000.glb"
                                }
                            }
                        ],
                        "boundingVolume": {
                            "sphere": [
                                -3161.8916502216409,
                                -1389.32667338685,
                                14.087869470605533,
                                622.4936580033902
                            ]
                        },
                        "geometricError": 9.72484660205246,
                        "refine": "REPLACE",
                        "content": {
                            "url": "Tile_-4735_15833_0000_0001_0000.glb"
                        }
                    }
                ],
                "boundingVolume": {
                    "sphere": [
                        -3161.8916502216409,
                        -1389.32667338685,
                        14.087869470605533,
                        622.4936580033902
                    ]
                },
                "geometricError": 9.72484660026178,
                "refine": "REPLACE",
                "content": {
                    "url": "Tile_-4735_15833_0000_0002_0000.glb"
                }
            }
        ],
        "boundingVolume": {
            "sphere": [
                -3161.8916502216409,
                -1389.32667338685,
                14.087869470605533,
                622.4936580033902
            ]
        },
        "geometricError": 9.724846598057957,
        "refine": "REPLACE",
        "content": {
            "url": "Tile_-4735_15833_0000.glb"
        }
    }
}
