{
    "asset": {
        "version": "1.1"
    },
    "root": {
        "children": [
            {
                "children": [
                    {
                        "children": [
                            {
                                "boundingVolume": {
                                    "sphere": [
                                        -3132.732447122922,
                                        -670.4878635620773,
                                        36.68588083359367,
                                        506.8821781224869
                                    ]
                                },
                                "geometricError": 81101.1494761604,
                                "refine": "REPLACE",
                                "content": {
                                    "url": "Tile_-4736_15833_0000_0000_0000.glb"
                                }
                            }
                        ],
                        "boundingVolume": {
                            "sphere": [
                                -3149.3854586610138,
                                -645.0313982863173,
                                26.379699793796346,
                                539.000269367903
                            ]
                        },
                        "geometricError": 8.420333152953616,
                        "refine": "REPLACE",
                        "content": {
                            "url": "Tile_-4736_15833_0000_0001_0000.glb"
                        }
                    }
                ],
                "boundingVolume": {
                    "sphere": [
                        -3149.177242726868,
                        -644.7413438979866,
                        26.27542640305266,
                        539.372234908564
                    ]
                },
                "geometricError": 8.4190267237478,
                "refine": "REPLACE",
                "content": {
                    "url": "Tile_-4736_15833_0000_0002_0000.glb"
                }
            }
        ],
        "boundingVolume": {
            "sphere": [
                -3149.0473267863505,
                -644.6057421865802,
                26.226574570665738,
                539.5662773710934
            ]
        },
        "geometricError": 8.419356568901911,
        "refine": "REPLACE",
        "content": {
            "url": "Tile_-4736_15833_0000.glb"
        }
    }
}
